metasip/__init__.py
metasip/_version.py
metasip/exceptions.py
metasip/main.py
metasip/gui/__init__.py
metasip/gui/main.py
metasip/gui/shell.py
metasip/gui/shell_tool.py
metasip/gui/helpers/__init__.py
metasip/gui/helpers/base_dialog.py
metasip/gui/helpers/project_ui.py
metasip/gui/helpers/question.py
metasip/gui/helpers/warning.py
metasip/gui/tools/__init__.py
metasip/gui/tools/helpers.py
metasip/gui/tools/import_project_tool.py
metasip/gui/tools/logger_tool.py
metasip/gui/tools/api_editor_tool/__init__.py
metasip/gui/tools/api_editor_tool/api_editor.py
metasip/gui/tools/api_editor_tool/api_editor_tool.py
metasip/gui/tools/api_editor_tool/external_editor.py
metasip/gui/tools/api_editor_tool/dialogs/__init__.py
metasip/gui/tools/api_editor_tool/dialogs/argument_properties_dialog.py
metasip/gui/tools/api_editor_tool/dialogs/callable_properties_dialog.py
metasip/gui/tools/api_editor_tool/dialogs/class_properties_dialog.py
metasip/gui/tools/api_editor_tool/dialogs/enum_member_properties_dialog.py
metasip/gui/tools/api_editor_tool/dialogs/enum_properties_dialog.py
metasip/gui/tools/api_editor_tool/dialogs/features_dialog.py
metasip/gui/tools/api_editor_tool/dialogs/helpers.py
metasip/gui/tools/api_editor_tool/dialogs/manual_code_dialog.py
metasip/gui/tools/api_editor_tool/dialogs/module_properties_dialog.py
metasip/gui/tools/api_editor_tool/dialogs/move_header_dialog.py
metasip/gui/tools/api_editor_tool/dialogs/namespace_properties_dialog.py
metasip/gui/tools/api_editor_tool/dialogs/opaque_class_properties_dialog.py
metasip/gui/tools/api_editor_tool/dialogs/platforms_dialog.py
metasip/gui/tools/api_editor_tool/dialogs/project_properties_dialog.py
metasip/gui/tools/api_editor_tool/dialogs/typedef_properties_dialog.py
metasip/gui/tools/api_editor_tool/dialogs/variable_properties_dialog.py
metasip/gui/tools/api_editor_tool/dialogs/versions_dialog.py
metasip/gui/tools/features_tool/__init__.py
metasip/gui/tools/features_tool/delete_feature_dialog.py
metasip-2.15.0.dist-info/licenses/LICENSE
metasip-2.15.0.dist-info/METADATA
metasip-2.15.0.dist-info/WHEEL
metasip-2.15.0.dist-info/entry_points.txt
metasip-2.15.0.dist-info/top_level.txt
metasip-2.15.0.dist-info/RECORD
