Metadata-Version: 2.4
Name: metasip
Version: 2.15.0
Summary: GUI Development Tool for SIP
Author-email: Phil Thompson <phil@riverbankcomputing.com>
License: Copyright 2024 Phil Thompson <phil@riverbankcomputing.com>
Project-URL: homepage, https://github.com/Python-SIP/metasip
Classifier: License :: OSI Approved :: BSD License
Requires-Python: >=3.8
License-File: LICENSE
Provides-Extra: gui
Requires-Dist: PyQt6; extra == "gui"
Requires-Dist: PyQt6-QScintilla; extra == "gui"
Dynamic: license-file
